rss_provider/__init__.py
rss_provider/configure.zcml
rss_provider/interfaces.py
rss_provider/permissions.zcml
rss_provider/profiles.zcml
rss_provider/testing.py
rss_provider/behaviors/__init__.py
rss_provider/behaviors/configure.zcml
rss_provider/browser/__init__.py
rss_provider/browser/configure.zcml
rss_provider/browser/rssfeed.py
rss_provider/browser/pt/rss_feed_view.pt
rss_provider/browser/static/.gitkeep
rss_provider/content/__init__.py
rss_provider/content/rss_feed.py
rss_provider/locales/__init__.py
rss_provider/locales/rss_provider.pot
rss_provider/locales/update.py
rss_provider/locales/en/LC_MESSAGES/rss_provider.po
rss_provider/profiles/default/browserlayer.xml
rss_provider/profiles/default/types.xml
rss_provider/profiles/default/types/.gitkeep
rss_provider/profiles/default/types/rss_feed.xml
rss_provider/profiles/uninstall/browserlayer.xml
rss_provider/setuphandlers/__init__.py
rss_provider/setuphandlers/images/plone-foundation.png
rss_provider/upgrades/__init__.py
rss_provider/upgrades/configure.zcml
rss_provider-1.1.0.dist-info/METADATA
rss_provider-1.1.0.dist-info/WHEEL
rss_provider-1.1.0.dist-info/entry_points.txt
rss_provider-1.1.0.dist-info/licenses/LICENSE.GPL
rss_provider-1.1.0.dist-info/licenses/LICENSE.md
rss_provider-1.1.0.dist-info/RECORD
